EZFinger/__init__.py
EZFinger/finger.py
PyEZFinger-1.2.dist-info/LICENSE
PyEZFinger-1.2.dist-info/METADATA
PyEZFinger-1.2.dist-info/WHEEL
PyEZFinger-1.2.dist-info/top_level.txt
PyEZFinger-1.2.dist-info/RECORD
