Metadata-Version: 2.1
Name: PyEZFinger
Version: 1.2
Summary: EZ finger recognizing
Home-page: UNKNOWN
Author: seonwoo0808
Author-email: seonwoo0808@naver.com
License: MIT
Platform: UNKNOWN
Classifier: Programming Language :: Python :: 3
Classifier: License :: OSI Approved :: MIT License
Classifier: Operating System :: OS Independent
License-File: LICENSE
